keepmeup/__init__.py
keepmeup/main.py
keepmeup-1.0.4.dist-info/entry_points.txt
keepmeup-1.0.4.dist-info/METADATA
keepmeup-1.0.4.dist-info/WHEEL
keepmeup-1.0.4.dist-info/RECORD
