Metadata-Version: 2.1
Name: keepmeup
Version: 1.0.4
Summary: Keep windows away from sleeping
Author: Michael Tai Wai Ho
Requires-Python: >=3.9,<4.0
Classifier: Programming Language :: Python :: 3
Classifier: Programming Language :: Python :: 3.9
Classifier: Programming Language :: Python :: 3.10
Classifier: Programming Language :: Python :: 3.11
Classifier: Programming Language :: Python :: 3.12
Requires-Dist: PySimpleGUI (>=4.60.5,<5.0.0)
Requires-Dist: pyautogui (>=0.9.54,<0.10.0)
